[
{"edit":"Haru", "num":"0", "page":56, "trad": "Ruk230", "ext": "jpg"},
{"edit":"Odds", "num":"1", "page":63, "trad": "Ruk230", "ext": "png"},
{"edit":"Odds", "num":"2", "page":64, "trad": "BCDT", "ext": "png"},
{"edit":"Odds", "num":"3", "page":69, "trad": "Ruk230", "ext": "png"},
{"edit":"Odds", "num":"4", "page":70, "trad": "BCDT", "ext": "png"},
{"edit":"Odds", "num":"6", "page":52, "trad": "Odds", "ext": "png"},
{"edit":"Odds", "num":"7", "page":58, "trad": "BCDT", "ext": "png"},
{"edit":"Odds", "num":"8", "page":53, "trad": "BCDT", "ext": "png"},
{"edit":"Odds", "num":"9", "page":63, "trad": "Odds", "ext": "png"},
{"edit":"Odds", "num":"10", "page":64, "trad": "BCDT", "ext": "png"},
{"edit":"Odds", "num":"11", "page":58, "trad": "Odds", "ext": "png"}
]